multi_comp_matrix/MCM.py
multi_comp_matrix/__init__.py
multi_comp_matrix/utils.py
multi_comp_matrix/tests/__init__.py
multi_comp_matrix/tests/test_mcm.py
multi_comp_matrix-0.0.4.dist-info/licenses/LICENSE
multi_comp_matrix-0.0.4.dist-info/METADATA
multi_comp_matrix-0.0.4.dist-info/WHEEL
multi_comp_matrix-0.0.4.dist-info/top_level.txt
multi_comp_matrix-0.0.4.dist-info/RECORD
