Metadata-Version: 2.4
Name: multi_comp_matrix
Version: 0.0.4
Summary:   Multi Comparison Matrix: A long term approach to benchmark evaluations  
Author-email: Ali Ismail-Fawaz <ali-el-hadi.ismail-fawaz@uha.fr>, Angus Dempster <Angus.Dempster1@monash.edu>, Chang Wei Tan <Chang.Tan@monash.edu>, Matthieu Herrmann <matthieu.herrmann@monash.edu>, Lynn Miller <lynn.miller1@monash.edu>, "Daniel F. Schmidt" <Daniel.Schmidt@monash.edu>, Stefano Berretti <stefano.berretti@unifi.it>, Jonathan Weber <jonathan.weber@uha.fr>, Maxime Devanne <maxime.devanne@uha.fr>, Germain Forestier <germain.forestier@uha.fr>, "Geoffrey I. Webb" <geoff.webb@monash.edu
Maintainer-email: Ali Ismail-Fawaz <ali-el-hadi.ismail-fawaz@uha.fr>, Angus Dempster <Angus.Dempster1@monash.edu>, Chang Wei Tan <Chang.Tan@monash.edu>
License: GPL-3.0-only
Keywords: data-science,machine-learning,data-mining,time-series,time-series-analysis,time-series-classification,time-series-regression,time-series-machine-learning,benchmarking,benchmarking-machine-learning
Classifier: Development Status :: 4 - Beta
Classifier: Intended Audience :: Developers
Classifier: License :: OSI Approved :: GNU General Public License v3 (GPLv3)
Classifier: Programming Language :: Python :: 3
Classifier: Programming Language :: Python :: 3.10
Classifier: Programming Language :: Python :: 3.11
Classifier: Programming Language :: Python :: 3.12
Requires-Python: >=3.10
License-File: LICENSE
Requires-Dist: numpy==1.26.4
Requires-Dist: pandas==2.2.3
Requires-Dist: matplotlib==3.7.4
Requires-Dist: scipy==1.11.4
Requires-Dist: baycomp==1.0
Requires-Dist: tqdm==4.66.1
Provides-Extra: dev
Requires-Dist: black; extra == "dev"
Requires-Dist: flake8; extra == "dev"
Requires-Dist: mypy; extra == "dev"
Requires-Dist: pytest; extra == "dev"
Requires-Dist: pytest-cov; extra == "dev"
Requires-Dist: pytest-xdist; extra == "dev"
Requires-Dist: pytest-timeout; extra == "dev"
Requires-Dist: pytest-rerunfailures; extra == "dev"
Requires-Dist: pre-commit; extra == "dev"
Dynamic: license-file
